{"required":["developers","publishers"],"type":"object","properties":{"platformName":{"type":["null","string"]},"platformSlug":{"type":["null","string"]},"releaseDate":{"type":["null","integer"],"format":"int64"},"region":{"type":["null","string"]},"human":{"type":["null","string"]},"developers":{"type":"array","items":{"required":["id","name","slug"],"type":"object","properties":{"id":{"type":"integer","format":"int64"},"name":{"type":"string"},"slug":{"type":["null","string"]}},"x-readme-ref-name":"CompanyInfoDto"}},"publishers":{"type":"array","items":{"required":["id","name","slug"],"type":"object","properties":{"id":{"type":"integer","format":"int64"},"name":{"type":"string"},"slug":{"type":["null","string"]}},"x-readme-ref-name":"CompanyInfoDto"}}},"x-readme-ref-name":"GameReleaseDto"}